CMDUI/CMDUI.py
CMDUI/__init__.py
CMDUI/colors.py
CMDUI/components.py
CMDUI/consolemanager.py
CMDUI/placementmanagement.py
CMDUI/variables.py
CMDUI/widgets.py
CMDUI/console/__init__.py
CMDUI/console/consolemanager.py
CMDUI/console/resizelistener.py
CMDUI/utils/__init__.py
CMDUI/utils/stoppablethread.py
CMDUI/utils/windowresizelistener.py
CMDUI-0.2.0.dist-info/LICENSE
CMDUI-0.2.0.dist-info/METADATA
CMDUI-0.2.0.dist-info/WHEEL
CMDUI-0.2.0.dist-info/top_level.txt
CMDUI-0.2.0.dist-info/RECORD
